__init__.py
DeepGapSeq/__init__.py
DeepGapSeq/_utils_worker.py
DeepGapSeq/ebFRET/__init__.py
DeepGapSeq/ebFRET/ebfret_utils.py
DeepGapSeq/simulation/__init__.py
DeepGapSeq/simulation/deepgapseq_trace_generator.py
DeepGapSeq/simulation/training_data_1color.py
DeepGapSeq/simulation/training_data_2color.py
DeepGapSeq/simulation/training_data_3color.py
DeepGapSeq/simulation/legacy code/__init__.py
DeepGapSeq/simulation/legacy code/generate_training_data_from_MATLAB.py
DeepGapSeq-0.0.1.dist-info/LICENCE
DeepGapSeq-0.0.1.dist-info/METADATA
DeepGapSeq-0.0.1.dist-info/WHEEL
DeepGapSeq-0.0.1.dist-info/entry_points.txt
DeepGapSeq-0.0.1.dist-info/top_level.txt
DeepGapSeq-0.0.1.dist-info/RECORD
